[
	{ "s": "OCCUR", "p": [70, 73, 76, 74, 72, 77, 71, 69] },
	{ "s": "OF", "p": [5, 9, 17, 10, 68, 6, 74, 72, 71, 35, 29, 67, 36, 21, 19, 16, 12, 11, 8, 3] },
	{ "s": "OFF", "p": [10, 74, 17] },
	{ "s": "OFFLINE", "p": [39] },
	{ "s": "OLD", "p": [29] },
	{ "s": "ON", "p": [9, 72, 15, 6, 74, 69, 21, 5, 73, 70, 26, 17, 10, 77, 76, 71, 68, 38, 29, 20, 19, 11, 3] },
	{ "s": "ONCE", "p": [6, 28, 15, 5] },
	{ "s": "ONE", "p": [72, 15, 11, 10, 9, 6] },
	{ "s": "ONLINE", "p": [69] },
	{ "s": "ONLY", "p": [69, 17, 5, 72, 8] },
	{ "s": "OPEN", "p": [5, 68, 26, 21, 14, 9] },
	{ "s": "OPENED", "p": [5] },
	{ "s": "OPENS", "p": [39, 9] },
	{ "s": "OPTION", "p": [74, 70, 69, 73, 17] },
	{ "s": "OPTIONALLY", "p": [8] },
	{ "s": "OPTIONS", "p": [17] },
	{ "s": "OR", "p": [9, 68, 5, 29, 15, 21, 19, 17, 72, 71, 16, 14, 6, 77, 74, 73, 70, 28, 18, 12, 10, 8, 3] },
	{ "s": "ORANGE", "p": [12] },
	{ "s": "ORDER", "p": [9, 5, 10, 70, 72, 36, 74, 71, 69, 63, 52, 11, 6, 76, 29, 8, 77, 73, 26, 21, 12, 4] },
	{ "s": "ORDERING", "p": [73, 70] },
	{ "s": "ORDERS", "p": [5, 21, 3, 74, 6, 77, 70, 69, 72, 20, 11] },
	{ "s": "ORGANIZATION", "p": [68] },
	{ "s": "ORIGINAL", "p": [29] },
	{ "s": "OTHER", "p": [76, 28, 15] },
	{ "s": "OTHERWISE", "p": [26] },
	{ "s": "OUT", "p": [71, 69, 38, 17, 9, 5] },
	{ "s": "OVER", "p": [9, 27, 16] },
	{ "s": "OVERLAP", "p": [15] }
]